torrent_download/Config.py
torrent_download/__init__.py
torrent_download/exceptions.py
torrent_download/download/QBittorrentDownloader.py
torrent_download/download/__init__.py
torrent_download/entities/TorrentDownload.py
torrent_download/entities/TorrentInfo.py
torrent_download/entities/__init__.py
torrent_download/search/NyaaSearchEngine.py
torrent_download/search/SearchEngine.py
torrent_download/search/__init__.py
torrent_download-0.0.1.data/scripts/tdl
torrent_download-0.0.1.data/scripts/tdl-browse
torrent_download-0.0.1.data/scripts/tdl-config-gen
torrent_download-0.0.1.data/scripts/tdl-search
torrent_download-0.0.1.dist-info/LICENSE
torrent_download-0.0.1.dist-info/METADATA
torrent_download-0.0.1.dist-info/WHEEL
torrent_download-0.0.1.dist-info/top_level.txt
torrent_download-0.0.1.dist-info/RECORD
