Metadata-Version: 2.1
Name: torrent-download
Version: 0.0.1
Summary: An torrent file downloader
Home-page: https://gitlab.namibsun.net/namibsun/python/torrent-download
Author: Hermann Krumrey
Author-email: hermann@krumreyh.com
License: GNU GPL3
Platform: UNKNOWN
Classifier: License :: OSI Approved :: GNU General Public License v3 (GPLv3)
Requires-Dist: bs4
Requires-Dist: requests
Requires-Dist: cfscrape
Requires-Dist: typing
Requires-Dist: colorama
Requires-Dist: python-qbittorrent
Requires-Dist: puffotter
Requires-Dist: sentry-sdk
